{
  "generatedAt": "2026-05-26T06:51:51.540Z",
  "staticItemCount": 1,
  "sources": [
    {
      "id": "nasa-launch-schedule",
      "status": "healthy",
      "fallbackUsed": false,
      "fetchedSeedCount": 3,
      "freshSeedCount": 3,
      "staleSeedCount": 0
    },
    {
      "id": "usgs-earthquakes",
      "status": "healthy",
      "fallbackUsed": false,
      "fetchedSeedCount": 214,
      "freshSeedCount": 1,
      "staleSeedCount": 0,
      "strongestMagnitude": 6.9,
      "largeCount": 13
    },
    {
      "id": "noaa-space-weather",
      "status": "healthy",
      "fallbackUsed": false,
      "fetchedSeedCount": 358,
      "freshSeedCount": 1,
      "staleSeedCount": 0,
      "latestKp": 0,
      "recentPeakKp": 1,
      "alertLevel": "quiet"
    }
  ]
}
