{
  "updatedAt": "2026-06-28T16:58:21.023Z",
  "items": [
    {
      "id": "tech-the-cube-is-jim-henson-s-little-known-proto-blac-342aa71b87",
      "title": "The Cube is Jim Henson’s little-known proto-Black Mirror masterpiece",
      "source": "The Verge",
      "url": "https://www.theverge.com/entertainment/958757/jim-henson-the-cube-black-mirror-tv-movie-review",
      "tag": "Technology",
      "publishedAt": "2026-06-28T16:30:00.000Z",
      "summary": "I'm sure we're all familiar with Dark Crystal, so we know that Jim Henson can be weird and tackle slightly more mature subject matter. But there is little in his oeuvre that is...",
      "whyItMatters": "Technology updates can influence strategy, risk, and the speed of change across digital products."
    },
    {
      "id": "tech-apple-s-touchscreen-macbook-reportedly-won-t-wai-e9f45539c1",
      "title": "Apple's touchscreen MacBook reportedly won't wait for the M7 chips",
      "source": "Engadget",
      "url": "https://www.engadget.com/2203348/apple-touchscreen-macbook-launch-before-m7-chips",
      "tag": "Technology",
      "publishedAt": "2026-06-28T16:20:44.000Z",
      "summary": "The new models will launch with the M5 Pro and M5 Max, according to Mark Gurman.",
      "whyItMatters": "Technology updates can influence strategy, risk, and the speed of change across digital products."
    },
    {
      "id": "tech-techcrunch-mobility-all-eyes-on-tesla-fsd-02255252a7",
      "title": "TechCrunch Mobility: All eyes on Tesla FSD",
      "source": "TechCrunch",
      "url": "https://techcrunch.com/2026/06/28/techcrunch-mobility-all-eyes-on-tesla-fsd",
      "tag": "Technology",
      "publishedAt": "2026-06-28T16:05:00.000Z",
      "summary": "Welcome back to TechCrunch Mobility, your hub for the future of transportation and now, more than ever, how AI is playing a part.",
      "whyItMatters": "Technology updates can influence strategy, risk, and the speed of change across digital products."
    }
  ]
}
