{
  "updatedAt": "2026-06-27T23:54:23.439Z",
  "items": [
    {
      "id": "tech-tech-firms-are-blaming-ai-for-mega-device-and-co-b7e87e01a6",
      "title": "Tech firms are blaming AI for mega device and console price rises",
      "source": "BBC Technology",
      "url": "https://www.bbc.co.uk/news/articles/cd95k584pzqo?at_medium=RSS&at_campaign=rss",
      "tag": "Technology",
      "publishedAt": "2026-06-27T23:10:47.000Z",
      "summary": "Xbox consoles, Nintendo's new Switch 2 and Valve's Steam Deck are just some of the gadgets seeing price hikes in recent months.",
      "whyItMatters": "Technology updates can influence strategy, risk, and the speed of change across digital products."
    },
    {
      "id": "tech-instagram-is-testing-more-ways-to-customize-your-2fd2f713be",
      "title": "Instagram is testing more ways to customize ‘Your Algorithm’",
      "source": "TechCrunch",
      "url": "https://techcrunch.com/2026/06/27/instagram-is-testing-more-ways-for-users-to-customize-your-algorithm",
      "tag": "Technology",
      "publishedAt": "2026-06-27T21:27:37.000Z",
      "summary": "Instagram users could soon see more ways to tune their content.",
      "whyItMatters": "Technology updates can influence strategy, risk, and the speed of change across digital products."
    },
    {
      "id": "tech-teenage-engineering-adds-lo-fi-mode-usb-audio-an-14bcee1d5b",
      "title": "Teenage Engineering adds lo-fi mode, USB audio, and more to its KO II sampler",
      "source": "The Verge",
      "url": "https://www.theverge.com/entertainment/958723/teenage-engineering-os-25-ep-133-ko-ii-sampler",
      "tag": "Technology",
      "publishedAt": "2026-06-27T21:20:32.000Z",
      "summary": "Teenage Engineering has already issued multiple substantial updates for its surprisingly capable $329 EP-133 KO II sampler. Its latest is one of the biggest yet. OS 2.5 adds aud...",
      "whyItMatters": "Technology updates can influence strategy, risk, and the speed of change across digital products."
    }
  ]
}
