{
  "updatedAt": "2026-07-16T20:51:03.174Z",
  "items": [
    {
      "id": "tech-samsung-s-55-inch-frame-art-tv-is-200-cheaper-th-6fd7abd9e9",
      "title": "Samsung’s 55-inch Frame art TV is $200 cheaper than usual",
      "source": "The Verge",
      "url": "https://www.theverge.com/gadgets/966613/samsung-the-frame-art-tv-deal-sale",
      "tag": "Technology",
      "publishedAt": "2026-07-16T20:47:30.000Z",
      "summary": "Samsung’s Frame is different from your average 4K TV. Its biggest selling point involves what it does when you aren’t actively using it. It can display art, turning your living...",
      "whyItMatters": "Technology updates can influence strategy, risk, and the speed of change across digital products."
    },
    {
      "id": "tech-do-face-masks-help-with-wildfire-smoke-yes-but-m-fa88802f93",
      "title": "Do Face Masks Help With Wildfire Smoke? Yes, But More Is Needed",
      "source": "Wired",
      "url": "https://www.wired.com/story/wildfire-smoke-safety-guide",
      "tag": "Technology",
      "publishedAt": "2026-07-16T20:41:10.000Z",
      "summary": "As wildfire smoke threatens air quality and safety for millions, here’s your playbook to keep your family safe from the damaging effects of smoke.",
      "whyItMatters": "Technology updates can influence strategy, risk, and the speed of change across digital products."
    },
    {
      "id": "tech-mlb-bans-using-dugout-ipads-for-ai-powered-in-ga-b05b862e14",
      "title": "MLB bans using dugout iPads for AI-powered in-game strategy calls",
      "source": "Engadget",
      "url": "https://www.engadget.com/2217032/mlb-bans-using-dugout-ipads-for-ai-powered-in-game-strategy-calls",
      "tag": "Technology",
      "publishedAt": "2026-07-16T20:26:13.000Z",
      "summary": "You're out, chatbots.",
      "whyItMatters": "Technology updates can influence strategy, risk, and the speed of change across digital products."
    }
  ]
}
