{
  "updatedAt": "2026-07-16T01:44:27.395Z",
  "items": [
    {
      "id": "tech-infinix-note-60-pro-pininfarina-edition-first-im-5e88c7c8d7",
      "title": "Infinix Note 60 Pro Pininfarina Edition First Impressions",
      "source": "Gadgets 360",
      "url": "https://www.gadgets360.com/mobiles/reviews/infinix-note-60-pro-pininfarina-edition-first-impressions-11775306",
      "tag": "Technology",
      "publishedAt": "2026-07-16T01:33:01.000Z",
      "summary": "The Infinix Note 60 Pro Pininfarina Edition appears to build upon the regular model by giving it an identity that feels different. Instead of relying on the branding alone, it a...",
      "whyItMatters": "Technology updates can influence strategy, risk, and the speed of change across digital products."
    },
    {
      "id": "tech-why-greylock-capped-its-new-fund-at-1-5b-when-it-4bfcb5732c",
      "title": "Why Greylock capped its new fund at $1.5B when it says it could have raised more",
      "source": "TechCrunch",
      "url": "https://techcrunch.com/2026/07/15/why-greylock-capped-its-new-fund-at-1-5b-when-it-says-it-could-have-raised-more",
      "tag": "Technology",
      "publishedAt": "2026-07-16T00:20:42.000Z",
      "summary": "By keeping the number of investments to about 25 per fund, Greylock aims to remain what it calls \"the most important partner\" to its founders.",
      "whyItMatters": "Technology updates can influence strategy, risk, and the speed of change across digital products."
    },
    {
      "id": "tech-skullcandy-s-bass-boosting-crusher-headphones-no-42ac25692a",
      "title": "Skullcandy’s bass-boosting Crusher headphones now come with Bose’s ANC",
      "source": "The Verge",
      "url": "https://www.theverge.com/tech/966022/skullcandy-cruser-1080-anc-bose-tuning-noise-cancelling-wireless-headphones",
      "tag": "Running",
      "publishedAt": "2026-07-16T00:00:00.000Z",
      "summary": "Skullcandy announced a new version of its Crusher wireless headphones today featuring a few of Bose's audio technologies including its QuietControl ANC and head-tracking spatial...",
      "whyItMatters": "Technology updates can influence strategy, risk, and the speed of change across digital products."
    }
  ]
}
