{
  "updatedAt": "2026-07-18T16:41:16.729Z",
  "section": "Top 3 Sports",
  "items": [
    {
      "id": "sports-no-panic-but-celtic-not-good-enough-yet-lambert-840c1590e9",
      "title": "No panic, but Celtic not good enough yet - Lambert",
      "source": "BBC Sport",
      "url": "https://www.bbc.co.uk/sport/football/articles/cz7dj84x49po?at_medium=RSS&at_campaign=rss",
      "tag": "Football",
      "publishedAt": "2026-07-18T16:29:25.000Z",
      "summary": "Paul Lambert believes former club Celtic are \"nowhere near good enough\" without further recruitment but has guarded against \"panic\".",
      "whyItMatters": "Football creates regular global sports momentum and quick-return storylines."
    },
    {
      "id": "sports-expert-world-cup-predictions-for-the-spain-argen-8b42a26cb1",
      "title": "Expert World Cup Predictions For The Spain-Argentina Final",
      "source": "Fox Sports",
      "url": "https://www.foxsports.com/stories/soccer/world-cup-predictions-spain-argentina-final-picks-messi-yamal",
      "tag": "Sports",
      "publishedAt": "2026-07-18T16:26:50.000Z",
      "summary": "Our World Cup experts make their picks with final score predictions for Sunday's Spain-Argentina final.",
      "whyItMatters": "It adds variety to the sports mix without turning the page into a full sports wire."
    },
    {
      "id": "sports-david-willey-somerset-looked-like-they-thought-t-136e30c910",
      "title": "David Willey: 'Somerset looked like they thought they'd won it'",
      "source": "ESPNcricinfo",
      "url": "https://www.cricinfo.com/ci/content/story/1546119.html?ex_cid=OTC-RSS",
      "tag": "Cricket",
      "publishedAt": "2026-07-18T16:20:18.000Z",
      "summary": "\"That's like a red rag to a bull to me,\" says Northants captain after inspiring turnaround win",
      "whyItMatters": "Cricket gives XLB a stronger India-relevant sports lane and a reason for repeat sports check-ins."
    }
  ]
}
