{
  "updatedAt": "2026-03-16T01:58:40.392Z",
  "section": "Top 3 Sports",
  "items": [
    {
      "id": "sports-a-moment-he-ll-never-forget-rooney-on-dowman-goa-0b2d8f1e06",
      "title": "'A moment he'll never forget' - Rooney on Dowman goal",
      "source": "BBC Sport",
      "url": "https://www.bbc.com/sport/football/videos/c626p4gjvz2o?at_medium=RSS&at_campaign=rss",
      "tag": "Football",
      "publishedAt": "2026-03-16T00:11:00.000Z"
    },
    {
      "id": "sports-sinner-matches-federer-djokovic-with-indian-well-f23c05eaa7",
      "title": "Sinner matches Federer & Djokovic with Indian Wells win",
      "source": "BBC Sport",
      "url": "https://www.bbc.com/sport/tennis/articles/cze047z42kgo?at_medium=RSS&at_campaign=rss",
      "tag": "Tennis",
      "publishedAt": "2026-03-15T23:51:23.000Z"
    },
    {
      "id": "sports-james-praises-doncic-after-overtime-lakers-winne-2efe0ac5fd",
      "title": "James praises Doncic after overtime Lakers winner",
      "source": "BBC Sport",
      "url": "https://www.bbc.com/sport/basketball/articles/c15xj0pjlddo?at_medium=RSS&at_campaign=rss",
      "tag": "Basketball",
      "publishedAt": "2026-03-15T07:28:09.000Z"
    }
  ]
}
