{
  "updatedAt": "2026-04-24T23:29:52.944Z",
  "section": "Top 3 Sports",
  "items": [
    {
      "id": "sports-2026-nba-draft-declarations-tracker-duke-s-camer-3fc99fb019",
      "title": "2026 NBA Draft Declarations Tracker: Duke's Cameron Boozer Declares",
      "source": "Fox Sports",
      "url": "https://www.foxsports.com/stories/college-basketball/2026-nba-draft-declarations-tracker",
      "tag": "Sports",
      "publishedAt": "2026-04-24T23:25:40.000Z",
      "summary": "Here are the notable college basketball players who have declared for the 2026 NBA Draft.",
      "whyItMatters": "It adds variety to the sports mix without turning the page into a full sports wire."
    },
    {
      "id": "sports-alex-de-minaur-s-horror-run-continues-with-loss--9e2cd0390e",
      "title": "Alex de Minaur’s horror run continues with loss to Spanish teenager Rafael Jodar in Madrid",
      "source": "The Guardian",
      "url": "https://www.theguardian.com/sport/2026/apr/25/alex-de-minaur-rafael-jodar-madrid-open-second-round-report",
      "tag": "Tennis",
      "publishedAt": "2026-04-24T23:07:24.000Z",
      "summary": "Australia No 1 defeated 6-3 6-1 by 19-year-old in second round World No 8 has lost six of past 10 matches in alarming stretch of form Alex de Minaur has suffered a startling def...",
      "whyItMatters": "It adds variety to the sports mix without turning the page into a full sports wire."
    },
    {
      "id": "sports-all-eyes-on-spurs-west-ham-unbelievable-forest-e-88b7d4303f",
      "title": "All eyes on Spurs & West Ham? 'Unbelievable' Forest edge towards safety",
      "source": "BBC Sport",
      "url": "https://www.bbc.com/sport/football/articles/c30rgm097vyo?at_medium=RSS&at_campaign=rss",
      "tag": "Football",
      "publishedAt": "2026-04-24T22:29:28.000Z",
      "summary": "After Nottingham Forest's stunning win at Sunderland, is the Premier League relegation battle now a two-horse race?",
      "whyItMatters": "Football creates regular global sports momentum and quick-return storylines."
    }
  ]
}
